[
    {
        "id": "7478e1ddaff31ed070c89f6b7d2075c3544e1f8eaf68b16a27ff4c5ddc559859",
        "title": "Seoul Says Deal Reached With U.S. to Release Workers Detained in Hyundai Raid",
        "summary": "U.S. border czar says such workplace raids will continue, as South Korea says a plane will be sent to repatriate the workers taken into custody in Georgia.",
        "source": "wsj",
        "date": "2025-09-08T10:07:00+09:00",
        "url": "https://www.wsj.com/world/asia/seoul-says-it-has-reached-deal-with-u-s-to-release-workers-detained-in-hyundai-raid-5048b38c",
        "reportUrl": ""
    },
    {
        "id": "5881a55d0a75493715c917f1369d4c7fa7f9f61f90eaa59cd2afbbdc89b69dbe",
        "title": "West Point Alumni Group Cancels Award Honoring Tom Hanks",
        "summary": "The group was to bestow the Sylvanus Thayer Award on the actor, but it said it was canceling the event to focus on preparing academy cadets for the future.",
        "source": "nytimes",
        "date": "2025-09-08T10:02:47+09:00",
        "url": "https://www.nytimes.com/2025/09/07/us/politics/tom-hanks-west-point-award.html",
        "reportUrl": ""
    },
    {
        "id": "358f4929e2256840d6ad87a98551bd4fec57500b098a4e3194b587d48fb828c4",
        "title": "The oil tycoons who backed Trump are getting nearly everything they wanted. “We all voted for this.”",
        "summary": "The Trump administration has opened land to drilling and is moving to roll back environmental restrictions and hobble renewable energy. But crude prices have dropped.",
        "source": "wsj",
        "date": "2025-09-08T10:00:00+09:00",
        "url": "https://www.wsj.com/politics/policy/trump-oil-industry-executives-policies-85eb74e6",
        "reportUrl": ""
    },
    {
        "id": "276ebbbc4beb0ed7f74ee21abaafa66858afcc0cb8602c9664f10bd0102f2f20",
        "title": "Australian Woman, Erin Patterson, Gets Life in Mushroom Murder Case",
        "summary": "Erin Patterson was found guilty of murdering three of her husband’s relatives and trying to kill a fourth by serving them deadly mushrooms.",
        "source": "nytimes",
        "date": "2025-09-08T09:22:05+09:00",
        "url": "https://www.nytimes.com/2025/09/07/world/australia/australia-mushroom-murder-erin-patterson.html",
        "reportUrl": ""
    },
    {
        "id": "058ded0a5dc411bed6c578ca86969346333b5f23266740149a4136d97962e9a7",
        "title": "Trump Is Met With Mostly Boos at U.S. Open as Security Delays a Match",
        "summary": "With the president in attendance at Arthur Ashe Stadium, the men’s final began as hundreds of people were still waiting to go through security screening.",
        "source": "nytimes",
        "date": "2025-09-08T07:47:39+09:00",
        "url": "https://www.nytimes.com/2025/09/07/us/politics/trump-us-open-tennis-boos-delays.html",
        "reportUrl": ""
    },
    {
        "id": "8004fb48b8037583e39a877a26fe1a144dd84745bb91a2569df8892dac13c132",
        "title": "Millions of Londoners Brace for Transit Disruption as Tube Strike Begins",
        "summary": "A strike on the London Underground began Sunday over pay and conditions, threatening to upend commuter journeys for most of the week.",
        "source": "nytimes",
        "date": "2025-09-08T06:37:53+09:00",
        "url": "https://www.nytimes.com/2025/09/07/world/europe/london-tube-strike.html",
        "reportUrl": ""
    },
    {
        "id": "bcfdafab18c980d6857c5c3310893c49f1369339fb98896f73996cb54502e481",
        "title": "RFK Jr., Rejecting Vaccine Data, Fuels Distrust of Public Health Agencies",
        "summary": "By promoting suspicions about the institutions he oversees, critics say Robert F. Kennedy Jr. is jeopardizing public health. He says he is pursuing transparency.",
        "source": "nytimes",
        "date": "2025-09-08T06:30:12+09:00",
        "url": "https://www.nytimes.com/2025/09/07/us/politics/kennedy-health-vaccines-cdc.html",
        "reportUrl": ""
    },
    {
        "id": "62668c7e6672b6995f5c39fc37e3515b10dc183a6f7e3ff5b5c9a664d304433b",
        "title": "Brazilians Protest as Bolsonaro Coup Trial Nears Verdict",
        "summary": "Tensions are heating up in Brazil as the nation enters the final week of former President Jair Bolsonaro’s trial on attempted coup charges.",
        "source": "nytimes",
        "date": "2025-09-08T05:47:28+09:00",
        "url": "https://www.nytimes.com/2025/09/07/world/americas/brazil-bolsonaro-trial-protests.html",
        "reportUrl": ""
    },
    {
        "id": "a473fd1fb61e8c46bd7a072997f6c719a743ce4301b045ec8a4c315b9280738f",
        "title": "Opinion | A Senate Confirmation Fast Lane?",
        "summary": "As obstruction undermines Senate advise and consent, Republicans consider a rule change to speed confirmation of Trump picks.",
        "source": "wsj",
        "date": "2025-09-08T05:34:00+09:00",
        "url": "https://www.wsj.com/opinion/a-senate-confirmation-fast-lane-presidential-nominees-2c548531",
        "reportUrl": ""
    },
    {
        "id": "76e0c51f1b1dc63201b2b5794b4b9e0839dceae1e8dec289d656b11e309ff497",
        "title": "Opinion | Brandon Johnson’s Other Chicago Mess",
        "summary": "The school board votes down his payday loan for pension costs.",
        "source": "wsj",
        "date": "2025-09-08T05:32:00+09:00",
        "url": "https://www.wsj.com/opinion/brandon-johnson-chicago-public-schools-loan-teachers-union-dc9cafbc",
        "reportUrl": ""
    },
    {
        "id": "0571a451b88fa5e93bc4137d043c73e9e36a471b5ef62c054c020fbcb3b5866f",
        "title": "Opinion | ‘War Department’ Is a Good Start",
        "summary": "Let’s avoid euphemism and give every agency of government an honest name.",
        "source": "wsj",
        "date": "2025-09-08T05:27:00+09:00",
        "url": "https://www.wsj.com/opinion/war-department-is-a-good-start-e8b7f360",
        "reportUrl": ""
    },
    {
        "id": "ff7f9fd0b9cde51c3491a8f4606ae6b80a263d596cbfa28cfe089875019e59f3",
        "title": "Opinion | Do Sports Explain the ‘Math Gender Gap’?",
        "summary": "Statistics and other numbers are pervasive in organized athletics.",
        "source": "wsj",
        "date": "2025-09-08T05:26:00+09:00",
        "url": "https://www.wsj.com/opinion/do-sports-explain-the-math-gender-gap-eecb0dbe",
        "reportUrl": ""
    },
    {
        "id": "ca98479853f89613c7baa169e802c18fe0163461cc0f6eaea7fe4b17454f58c2",
        "title": "Hyundai Raid Rattles a Hot Spot of Growth in Georgia",
        "summary": "Koreans drawn to communities around the carmaker’s complex now wonder if they are welcome.",
        "source": "wsj",
        "date": "2025-09-08T05:22:00+09:00",
        "url": "https://www.wsj.com/us-news/hyundai-raid-rattles-a-hot-spot-of-growth-in-georgia-d1fcd585",
        "reportUrl": ""
    },
    {
        "id": "b7b50f8afbda9a36bc73ad0401ecd8fa3593ce02f05adaf9ba4b5855acec61d7",
        "title": "Opinion | Trump’s Risky Game With the Fed",
        "summary": "The U.S. built its economic credibility slowly over a long time. Once lost, it won’t be easy to regain.",
        "source": "wsj",
        "date": "2025-09-08T05:19:00+09:00",
        "url": "https://www.wsj.com/opinion/trumps-risky-game-with-the-fed-1d727c53",
        "reportUrl": ""
    },
    {
        "id": "62eb8cdfa3d20d09dcdb760d9d17e6747e0b60fcdefa06bbaf41c2abeba5c163",
        "title": "What We Know About the Hyundai-LG Plant Immigration Raid in Georgia",
        "summary": "Several hundred workers, most of them South Korean nationals, were detained at the construction site of a sprawling electric vehicle battery plant on Thursday.",
        "source": "nytimes",
        "date": "2025-09-08T04:22:32+09:00",
        "url": "https://www.nytimes.com/2025/09/07/us/politics/hyundai-plant-immigration-raid-georgia.html",
        "reportUrl": ""
    },
    {
        "id": "82366a54ffe2a6f312ea43a9b798d8629feb9bec2d503b6697a3a22bc21962e2",
        "title": "Trump Downplays Post Threatening Chicago, Saying He Wants to ‘Clean Up’ City",
        "summary": "The president had said on social media that Chicago was “about to find out why it’s called the Department of WAR,” drawing a fierce rebuke from Democrats.",
        "source": "nytimes",
        "date": "2025-09-08T04:19:44+09:00",
        "url": "https://www.nytimes.com/2025/09/07/us/politics/trump-chicago-war-us-open.html",
        "reportUrl": ""
    },
    {
        "id": "dd16a2ce6489baa2167bc6c92a54aded73422b7d446b91ebeca4d9072c7f4443",
        "title": "Houthi Drone Hits Israeli Airport After Warning System Failure",
        "summary": "The strike by the Yemeni militants followed the Israeli killing of several of their top leaders a week ago.",
        "source": "nytimes",
        "date": "2025-09-08T04:16:22+09:00",
        "url": "https://www.nytimes.com/2025/09/07/world/middleeast/houthi-drone-israeli-airport.html",
        "reportUrl": ""
    },
    {
        "id": "9adcbe6a85736420ba0721dbc372a11b2e5af111fd6026664767da74e0326a84",
        "title": "Russia Strikes Ukraine Government Building in Largest Drone Assault of War",
        "summary": "Ukrainians said it was the first time a key building in Kyiv’s government district had been damaged since the war began. Russia has kept attacking despite Trump administration efforts at peace talks.",
        "source": "nytimes",
        "date": "2025-09-08T03:45:35+09:00",
        "url": "https://www.nytimes.com/2025/09/07/world/europe/russian-strike-kyiv-ukraine.html",
        "reportUrl": ""
    },
    {
        "id": "00730141f68bfbcd11d13365c13b99e5bca4219e677c2a186cd8638cc6d43939",
        "title": "A Town Reluctantly Let a Mosque Expand. Then Came the Backlash.",
        "summary": "A Long Island town board failed to approve a settlement its lawyers had struck with Masjid Al-Baqi after a yearslong dispute tainted by bigotry. The mosque’s federal suit will be heard next month.",
        "source": "nytimes",
        "date": "2025-09-08T03:23:39+09:00",
        "url": "https://www.nytimes.com/2025/09/07/nyregion/oyster-bay-mosque-lawsuit.html",
        "reportUrl": ""
    },
    {
        "id": "6c98e7d210c28d2421bd89c07fa3c298592387a440367bcc156b4b857310d87e",
        "title": "Chicago on Edge After Threats of ICE Raids",
        "summary": "President Trump is threatening the third-largest U.S. city with “Chipocalypse Now” and mass deportations.",
        "source": "wsj",
        "date": "2025-09-08T03:16:00+09:00",
        "url": "https://www.wsj.com/us-news/chicago-on-edge-after-threats-of-ice-raids-19f59ed4",
        "reportUrl": ""
    },
    {
        "id": "5bb45deac5ad915acc2547a3fd9a50676e8a32d3ce6fb1be5a6034f3bdfe1438",
        "title": "Opinion | America’s ‘Buy Now, Pay Later’ Economy",
        "summary": "Signs of an emerging debt crisis are everywhere—from credit cards and mortgages to government budgets.",
        "source": "wsj",
        "date": "2025-09-08T02:20:00+09:00",
        "url": "https://www.wsj.com/opinion/americas-buy-now-pay-later-economy-3dae0902",
        "reportUrl": ""
    },
    {
        "id": "94e9e5b9538cbecd660dd59aaf31fbf697cda2a5905d2ce81b995847cc09e91f",
        "title": "Egypt-Israel Tensions Rise Over Attack on Gaza City",
        "summary": "A large-scale Israeli assault on the city in northern Gaza could push hundreds of thousands of Palestinians southward toward Egypt’s border.",
        "source": "nytimes",
        "date": "2025-09-08T01:37:49+09:00",
        "url": "https://www.nytimes.com/2025/09/07/world/middleeast/egypt-israel-gaza-city.html",
        "reportUrl": ""
    },
    {
        "id": "e687323d9c328ae523a852302c12741306e20dfff1e00810817ae1f44a90e403",
        "title": "Immigration Raid Exposes Tensions From Seoul to Washington to Rural Georgia",
        "summary": "The raid at a Georgia plant being built with heavy investment from South Korea reveals strain as a rush to expand manufacturing in the United States clashes with an immigration crackdown.",
        "source": "nytimes",
        "date": "2025-09-07T20:47:39+09:00",
        "url": "https://www.nytimes.com/2025/09/06/us/immigration-raid-georgia.html",
        "reportUrl": ""
    },
    {
        "id": "62ed1e1eaabd74d3f20692606ee44b030d6a1ba4ce7c338510959cb8dacd0438",
        "title": "‘If I Live to 25, I’ve Lived a Good Life’",
        "summary": "He started fighting wildfires as a teenager. After inhaling smoke on the front lines for six seasons, he faced an impossible choice.",
        "source": "nytimes",
        "date": "2025-09-07T19:24:11+09:00",
        "url": "https://www.nytimes.com/2025/09/07/us/wildfire-firefighter-cancer.html",
        "reportUrl": ""
    },
    {
        "id": "910b9698b51038fc1d8768bcd674f3b20d57f698fc27834e564c626e938a06ff",
        "title": "Alleged Chinese cyber-espionage campaigns were timed to potentially deploy spyware against organizations giving input on President Trump’s trade negotiations",
        "summary": "The FBI is investigating a scheme to spy on trade groups using fake emails from China committee chair Rep. John Moolenaar.",
        "source": "wsj",
        "date": "2025-09-07T18:30:00+09:00",
        "url": "https://www.wsj.com/politics/national-security/china-trade-talks-spy-5c4801ca",
        "reportUrl": ""
    },
    {
        "id": "39d6c160ae7aeba3372a5e360aec8b21882f5cd99e968de14a4688aefb7ba3aa",
        "title": "A Six-Story Apartment Building Is Tearing This Small California Town Apart",
        "summary": "A community in Marin County is struggling to comply with state mandates for more housing; ‘When you move to a small town, you don’t come to live with a tower.’",
        "source": "wsj",
        "date": "2025-09-07T18:30:00+09:00",
        "url": "https://www.wsj.com/real-estate/a-six-story-apartment-building-is-tearing-this-small-california-town-apart-59f924ae",
        "reportUrl": ""
    },
    {
        "id": "ac06737e243d4c25ad87ec61c25722323a4abf1da5cfac889474f7235cfc1f50",
        "title": "Why Are More Older People Dying After Falls?",
        "summary": "Some researchers suspect that rising prescription drug use may explain a disturbing trend.",
        "source": "nytimes",
        "date": "2025-09-07T18:02:22+09:00",
        "url": "https://www.nytimes.com/2025/09/07/health/falls-deaths-elderly-drugs.html",
        "reportUrl": ""
    },
    {
        "id": "17d50a7e2dcc7955930b04e159935a0016addceb2d4681d786e9b4cc1854d2cf",
        "title": "Russia Steps Up Disinformation Efforts as Trump Abandons Resistance",
        "summary": "The Kremlin has begun a campaign to sway the parliamentary election in Moldova in what could become a new model of election interference online.",
        "source": "nytimes",
        "date": "2025-09-07T18:02:11+09:00",
        "url": "https://www.nytimes.com/2025/09/07/business/russia-disinformation-trump.html",
        "reportUrl": ""
    },
    {
        "id": "5d317bd80dd3c2ee0debc83950cae2ea4a1b4df5c62e2a3f75a69ac8b0e027ad",
        "title": "Stop Acting Like This Is Normal",
        "summary": "Democrats aren’t powerless, and they don’t have to enable autocracy.",
        "source": "nytimes",
        "date": "2025-09-07T15:18:40+09:00",
        "url": "https://www.nytimes.com/2025/09/07/opinion/trump-senate-democrats-shutdown.html",
        "reportUrl": ""
    },
    {
        "id": "fa2f7eeb4c0b305fec5ce0b256155e52fc83b6a98aa2d8e9c01d6d052345c157",
        "title": "The Future Is Flag Football",
        "summary": "Flag football offers girls as well as boys a means of enjoying the sport without the risk of brain damage.",
        "source": "nytimes",
        "date": "2025-09-07T14:00:08+09:00",
        "url": "https://www.nytimes.com/2025/09/07/opinion/nfl-flag-football.html",
        "reportUrl": ""
    },
    {
        "id": "62c9d00eff1f54753fc106bd0a84533d45a5f2f73e9e6ca9f3f8224dcecf0f98",
        "title": "Trump has so far stood by RFK Jr., the health and human services secretary, as he moves to dismantle public health institutions and overhaul U.S. vaccine policy",
        "summary": "Kennedy’s disruption of the CDC, vaccine recommendations and other policies drew a Senate rebuke. Trump is standing by him, for now.",
        "source": "wsj",
        "date": "2025-09-07T10:00:00+09:00",
        "url": "https://www.wsj.com/politics/policy/trump-said-rfk-jr-could-go-wild-the-health-secretary-is-testing-the-limits-e118dc87",
        "reportUrl": ""
    },
    {
        "id": "ec779947fea9c92f4aefe9124c7361f93c72c841b07740fb36d45b2643653829",
        "title": "A Mysterious Death Casts a Shadow Over Burning Man",
        "summary": "This year’s desert arts and music event reached a fever pitch before a Russian man was found in a pool of his own blood. Authorities said his death is being treated as a homicide.",
        "source": "wsj",
        "date": "2025-09-07T09:00:00+09:00",
        "url": "https://www.wsj.com/us-news/a-mysterious-death-casts-a-shadow-over-burning-man-e1bb702a",
        "reportUrl": ""
    },
    {
        "id": "22050cc07e98ebc8c6294b0b1aa53cdbae07481eb73a9f36b7b45ca22dd195ce",
        "title": "On College Campuses, Students Weigh the Risk of Resistance",
        "summary": "University administrations are under pressure from the Trump administration to discourage pro-Palestinian demonstrations.",
        "source": "wsj",
        "date": "2025-09-07T01:00:00+09:00",
        "url": "https://www.wsj.com/us-news/education/college-protest-risk-e5481800",
        "reportUrl": ""
    }
]