[
    {
        "id": "ced17ecfb90b4aefdd32f68ec1765ea4c7fdfa327cf7106a85d6a37bd12dc65e",
        "title": "北, 평양 골프 관광 홍보… \"유리한 자연지리적 조건\"",
        "summary": "(서울=연합뉴스) 이은정 기자 = 외화벌이를 위해 관광 산업을 확대하려는 북한이 골프 관광을 홍보하고 나서 눈길을 끈다.",
        "source": "yna",
        "date": "2025-08-26T08:14:21+09:00",
        "url": "https://www.yna.co.kr/view/AKR20250826029700504",
        "reportUrl": ""
    },
    {
        "id": "9604e5359fe87227ee0eae1803689399fbe11875c95fdbf86dee41fa9ddcd05a",
        "title": "[한미정상회담] 美전문가 \"對北대화 중요성 동의…무역·안보 긴장 여전\"",
        "summary": "(워싱턴=연합뉴스) 이유미 특파원 = 미국 내 한반도 전문가인 웬디 커틀러 아시아소사이어티정책연구소(ASPI) 부회장은 25일(현지시간) 이뤄진...",
        "source": "yna",
        "date": "2025-08-26T07:59:37+09:00",
        "url": "https://www.yna.co.kr/view/AKR20250826033400071",
        "reportUrl": ""
    },
    {
        "id": "14d1a43aa59391f03d6a98d5875e93c51596e992dccfbc8f4211c7ddefab7b8a",
        "title": "트럼프, 주한미군기지 부지소유권 거론…\"연내 김정은 만나고파\"(종합2보)",
        "summary": "(워싱턴=연합뉴스) 홍정규 이유미 김동현 특파원 = 도널드 트럼프 미국 대통령은 25일(현지시간) 이재명 대통령과의 정상회담에서 주한미군 감축에...",
        "source": "yna",
        "date": "2025-08-26T07:22:02+09:00",
        "url": "https://www.yna.co.kr/view/AKR20250826014851071",
        "reportUrl": ""
    },
    {
        "id": "31f1f009be12f0dc522600b8601591fe15140a38bd582d636d0fb68751f562e9",
        "title": "북미정상회담 트럼프 통역 이연향, 李대통령과의 회담에도 등장",
        "summary": "(워싱턴=연합뉴스) 김동현 특파원 = 25일(현지시간) 미국 백악관에서 열린 한미 정상회담에서 도널드 트럼프 미국 대통령의 통역으로 익숙한 얼굴...",
        "source": "yna",
        "date": "2025-08-26T07:07:17+09:00",
        "url": "https://www.yna.co.kr/view/AKR20250826024000071",
        "reportUrl": ""
    },
    {
        "id": "c7a13fc8bada32b7d35ead5fa8ed8f0c442bc640ce5243ba3419e5f5afb09d6d",
        "title": "[북한날씨] 전 지역 흐리다가 오전부터 구름 많음",
        "summary": "(서울=연합뉴스) 이은정 기자 = 북한은 26일 전 지역이 흐리다가 오전부터 구름이 많겠다고 기상청이 예보했다.",
        "source": "yna",
        "date": "2025-08-26T06:39:23+09:00",
        "url": "https://www.yna.co.kr/view/AKR20250826020800504",
        "reportUrl": ""
    },
    {
        "id": "8dafca8779b5b4fc5c20b807776b7f4c3b64f8bc6842cfc4165d2d31aa477656",
        "title": "北, UFS연습에 거듭 반발…\"명백한 전쟁 의지의 표현\"",
        "summary": "(서울=연합뉴스) 이은정 기자 = 북한은 한미연합정례훈련인 &apos;을지 자유의 방패&apos;(UFS·을지프리덤실드) 연습 기간 미국 스텔스 전투기인 F-35...",
        "source": "yna",
        "date": "2025-08-26T06:27:59+09:00",
        "url": "https://www.yna.co.kr/view/AKR20250826018700504",
        "reportUrl": ""
    },
    {
        "id": "dfd570e81aefd6305b6172ca2a35f73d41f6f144e8048101cb01a301afdc4103",
        "title": "트럼프, 주한미군기지 부지소유권 거론…\"연내 김정은 만나고파\"(종합)",
        "summary": "(워싱턴=연합뉴스) 홍정규 이유미 김동현 특파원 = 도널드 트럼프 미국 대통령은 25일(현지시간) 이재명 대통령과의 정상회담에서 주한미군 감축에...",
        "source": "yna",
        "date": "2025-08-26T05:48:51+09:00",
        "url": "https://www.yna.co.kr/view/AKR20250826014800071",
        "reportUrl": ""
    },
    {
        "id": "eb8e9619dab7e1ff2f4ac3427341532d3f7f47ad941247afc35830ba16ea6d81",
        "title": "[한미정상회담] '2018 소환' 트럼프…李대통령, 북미대화 '페이스메이커' 나서나",
        "summary": "(워싱턴=연합뉴스) 임형섭 설승은 황윤기 기자 = 이재명 대통령과 도널드 트럼프 미국 대통령이 25일(현지시각) 한미정상회담을 계기로 북미대화 ...",
        "source": "yna",
        "date": "2025-08-26T05:32:17+09:00",
        "url": "https://www.yna.co.kr/view/AKR20250826013400001",
        "reportUrl": ""
    },
    {
        "id": "d3fd5de78e7f2ebb92227705d2f8ccd3fcea752991eda9685e676edfa81101d4",
        "title": "트럼프 '확장주의' 한국에도?…주한미군기지 소유권 언급 주목",
        "summary": "(워싱턴=연합뉴스) 조준형 특파원 = 도널드 트럼프 미국 대통령이 25일(현지시간) 백악관에서 열린 한미정상회담에서 주한미군 기지 부지에 대한 ...",
        "source": "yna",
        "date": "2025-08-26T04:57:00+09:00",
        "url": "https://www.yna.co.kr/view/AKR20250826012600071",
        "reportUrl": ""
    },
    {
        "id": "3f10e3469ed87ee776bac8898a203d44faaeac441ea73b8a787e3c89d8a47786",
        "title": "李 \"김정은 만나달라\" 트럼프 \"올해 만나고 싶다\"…조선협력도 논의(종합)",
        "summary": "(워싱턴=연합뉴스) 이유미 특파원·임형섭 설승은 황윤기 기자 = 이재명 대통령과 도널드 트럼프 미국 대통령이 25일(현지시간) 미국 워싱턴DC에...",
        "source": "yna",
        "date": "2025-08-26T04:49:24+09:00",
        "url": "https://www.yna.co.kr/view/AKR20250826010651001",
        "reportUrl": ""
    },
    {
        "id": "3e176c1574712431387a2b935f3101981622b4d089797b367213c8d39615d33d",
        "title": "트럼프, 북미정상회담 추진 권고에 \"좋은 일…올해 만나고 싶다\"(종합2보)",
        "summary": "(워싱턴=연합뉴스) 박성민 홍정규 이유미 특파원 = 도널드 트럼프 미국 대통령이 25일(현지시간) 북한 김정은 국무위원장과의 정상회담 추진 의지...",
        "source": "yna",
        "date": "2025-08-26T04:48:40+09:00",
        "url": "https://www.yna.co.kr/view/AKR20250826003552071",
        "reportUrl": ""
    },
    {
        "id": "8f8941580bdb7e8cfbe386df98f3000cf3c30eeef637a2e2e63e144a7cbcb971",
        "title": "李대통령 \"김정은 만나달라\"…트럼프 \"올해 만나고 싶다\"",
        "summary": "(워싱턴=연합뉴스) 이유미 특파원·임형섭 설승은 황윤기 기자 = 이재명 대통령과 도널드 트럼프 미국 대통령이 25일(현지시간) 미국 워싱턴DC에...",
        "source": "yna",
        "date": "2025-08-26T03:36:49+09:00",
        "url": "https://www.yna.co.kr/view/AKR20250826010600001",
        "reportUrl": ""
    },
    {
        "id": "dd21b60ba811c691b99c5262890e8dc3d2f593f94b7e16bc6ab817ad15adff2d",
        "title": "트럼프, '북미정상회담' 권고에 \"좋은 일…추진할 것\"(종합)",
        "summary": "(워싱턴=연합뉴스) 박성민 홍정규 특파원 = 도널드 트럼프 미국 대통령이 25일(현지시간) 북한 김정은 국무위원장과의 정상회담 재추진에 의지를 ...",
        "source": "yna",
        "date": "2025-08-26T02:36:44+09:00",
        "url": "https://www.yna.co.kr/view/AKR20250826003551071",
        "reportUrl": ""
    },
    {
        "id": "00881df3c37e1832b494c41925304b07c1e1b39f600711684c7a6ebcba9229f0",
        "title": "트럼프, 北김정은 언제 볼지 질문에 \"올해 만나고 싶다\"",
        "summary": "(워싱턴=연합뉴스) 이유미 특파원 = 도널드 트럼프 미국 대통령은 25일(현지시간) 북한 김정은 국무위원장과 올해 만나고 싶다고 말했다.",
        "source": "yna",
        "date": "2025-08-26T02:31:34+09:00",
        "url": "https://www.yna.co.kr/view/AKR20250826008400071",
        "reportUrl": ""
    },
    {
        "id": "a795782e582ffe98d090544fcd3da9a92019babf27c0a2ba180ed0c86ce8425a",
        "title": "[속보] 트럼프, 北김정은 언제 볼지 질문에 \"올해 만나고 싶다\"",
        "summary": "(",
        "source": "yna",
        "date": "2025-08-26T02:19:54+09:00",
        "url": "https://www.yna.co.kr/view/AKR20250826007500071",
        "reportUrl": ""
    },
    {
        "id": "19957ca63553f0b57e32c618f7fd8ac52b21801e1cd9ac43b4d22f639ee5ab04",
        "title": "[속보] 트럼프 \"우리는 북한과 분명 큰 진전 이룰 수 있어\"",
        "summary": "(",
        "source": "yna",
        "date": "2025-08-26T02:05:32+09:00",
        "url": "https://www.yna.co.kr/view/AKR20250826005900071",
        "reportUrl": ""
    },
    {
        "id": "982da8af16f14307a6f004e8817597f321e105282265312b678ef3b042199630",
        "title": "트럼프 \"한국은 군사 장비 큰 구매국…회담서 논의할 것\"",
        "summary": "(워싱턴=연합뉴스) 조준형 특파원 = 도널드 트럼프 미국 대통령은 25일(현지시간) 한미정상회담에서 &quot;한국은 (미국) 군사장비의 큰 구매국&quot;이라...",
        "source": "yna",
        "date": "2025-08-26T01:59:31+09:00",
        "url": "https://www.yna.co.kr/view/AKR20250826005100071",
        "reportUrl": ""
    },
    {
        "id": "b9c8c174eafa37e70437f67faab23bd617d6525c82688be68ac6839799896b8a",
        "title": "트럼프 \"北김정은과 좋은 관계…언젠가 다시 만나기를 고대\"",
        "summary": "(워싱턴=연합뉴스) 박성민 홍정규 특파원 = 도널드 트럼프 미국 대통령이 25일(현지시간) 북한 김정은 국무위원장과의 재회동에 대한 의지를 거듭...",
        "source": "yna",
        "date": "2025-08-26T01:41:06+09:00",
        "url": "https://www.yna.co.kr/view/AKR20250826002151071",
        "reportUrl": ""
    },
    {
        "id": "e8b24149f65873fcb84d6b84f1b77a2e00e25685a14d37f0f85df1d352f26372",
        "title": "[속보] 트럼프 \"北 김정은과 언젠가 만날 것…만나기를 원해\"",
        "summary": "(",
        "source": "yna",
        "date": "2025-08-26T01:10:25+09:00",
        "url": "https://www.yna.co.kr/view/AKR20250826002100071",
        "reportUrl": ""
    },
    {
        "id": "12bc2bc9133707f4d8da2ce50abb0704251cb312d727b919654435695636cbdd",
        "title": "[북한단신] 농근맹 간부들, 백두산 답사 행군",
        "summary": "(서울=연합뉴스) ▲ 전국 농근맹일군(간부)들과 초급선전 일군들의 백두산지구 혁명전적지답사 행군이 18∼24일 진행됐다고 25일 조선중앙통신이 ...",
        "source": "yna",
        "date": "2025-08-25T17:00:00+09:00",
        "url": "https://www.yna.co.kr/view/AKR20250825123600504",
        "reportUrl": ""
    },
    {
        "id": "8feaa0c4340f6c02a842b5c3231c731cc4a83b53eb1462d4b4cdd72f9e9a5027",
        "title": "안규백, '합참의장 교체론'에 \"軍지휘부 조속한 교체 필요\"",
        "summary": "(서울=연합뉴스) 이정현 김철선 기자 = 안규백 국방부 장관은 25일 &apos;평양 무인기&apos; 작전에 관여했다는 의혹이 제기된 김명수 합동참모본부 의장 ...",
        "source": "yna",
        "date": "2025-08-25T16:49:35+09:00",
        "url": "https://www.yna.co.kr/view/AKR20250825118500504",
        "reportUrl": ""
    },
    {
        "id": "b03dff85711742047147b94c1687270e35ed9e0132bb258cbcc9644c78c82aa2",
        "title": "\"평양에 '짝퉁 스벅'…3잔에 25달러\" 외국인이 들여다본 북한",
        "summary": "(서울=연합뉴스) 고일환 기자 = 북한에 일부 상위계층을 위한 서구식 소비문화가 존재한다는 외국인들의 증언이 나왔다.",
        "source": "yna",
        "date": "2025-08-25T15:22:32+09:00",
        "url": "https://www.yna.co.kr/view/AKR20250825104200009",
        "reportUrl": ""
    },
    {
        "id": "29fcc8f36972078a884495a1274e8171904bb44b12c9653d6bc04e2d067f46c2",
        "title": "[게시판] 한반도통일미래센터 광복80주년 기념 대국민 개방",
        "summary": "▲ 통일부 국립통일교육원 한반도통일미래센터(이하 통일미래센터)는 광복 80주년을 맞아 30일 &apos;광복의 빛, 한반도 평화와 통일을 비추다!&apos;를 주...",
        "source": "yna",
        "date": "2025-08-25T13:14:51+09:00",
        "url": "https://www.yna.co.kr/view/AKR20250825076000504",
        "reportUrl": ""
    },
    {
        "id": "2db92160c8b825bc113c02aaa4925952132b43cfa4393c7b35668c4c444caf6e",
        "title": "민주평통 22기 자문위원 2만2천명 위촉 절차 착수",
        "summary": "(서울=연합뉴스) 하채림 기자 = 민주평화통일자문회의사무처(이하 사무처)는 제22기 민주평화통일자문회의(이하 자문회의) 자문위원 위촉 절차를 시...",
        "source": "yna",
        "date": "2025-08-25T11:44:57+09:00",
        "url": "https://www.yna.co.kr/view/AKR20250825067800504",
        "reportUrl": ""
    },
    {
        "id": "4f583f2ea87ab02d7b92d9852835413bd0cd64b463cc7725b0de30fa0caf560e",
        "title": "정동영 \"과거 남북합의 기초로 남북관계 복원에 최선\"",
        "summary": "(서울=연합뉴스) 하채림 기자 = 정동영 통일부 장관은 &quot;정부는 과거 남북이 이룩한 소중한 합의를 주춧돌 삼아 무너진 남북 관계를 일으켜 세우기...",
        "source": "yna",
        "date": "2025-08-25T10:25:44+09:00",
        "url": "https://www.yna.co.kr/view/AKR20250825052600504",
        "reportUrl": ""
    },
    {
        "id": "8b90ceb327145c9162dce2a7350bdbbb074fef234f31e1e49e16dfcd00be2f0f",
        "title": "李대통령 \"北문제 제한없이 필요한 얘기 다 할 것…길 만들어야\"",
        "summary": "(워싱턴=연합뉴스) 임형섭 설승은 황윤기 기자 = 이재명 대통령은 24일(현지시간) 이번 한미정상회담에서 다뤄질 대북 정책 의제와 관련해 &quot;제한...",
        "source": "yna",
        "date": "2025-08-25T09:00:02+09:00",
        "url": "https://www.yna.co.kr/view/AKR20250825003500001",
        "reportUrl": ""
    },
    {
        "id": "33eb78a6d6d49ef47c3f3126f8076811c45b9934532b4feebc8cfa50380f98eb",
        "title": "[북한날씨] 전 지역 흐리고 비…\"많은 비 주의 경보\"",
        "summary": "(서울=연합뉴스) 이은정 기자 = 북한은 25일 전 지역이 흐리고 비가 내리겠다고 기상청이 예보했다.",
        "source": "yna",
        "date": "2025-08-25T06:41:28+09:00",
        "url": "https://www.yna.co.kr/view/AKR20250825007900504",
        "reportUrl": ""
    }
]